imswitch/__init__.py
imswitch/__main__.py
imswitch/_data/icon.ico
imswitch/_data/icon.png
imswitch/_data/libs/GPU_acc_recon.dll
imswitch/_data/libs/cudart64_90.dll
imswitch/_data/libs/opencv_core340.dll
imswitch/_data/libs/opencv_imgcodecs340.dll
imswitch/_data/libs/opencv_imgproc340.dll
imswitch/_data/user_defaults/README.txt
imswitch/_data/user_defaults/imcontrol_setups/README.txt
imswitch/_data/user_defaults/imcontrol_setups/example_coolLED.json
imswitch/_data/user_defaults/imcontrol_setups/example_monalisa.json
imswitch/_data/user_defaults/imcontrol_setups/example_sted.json
imswitch/_data/user_defaults/imcontrol_slm/info_glyc.json
imswitch/_data/user_defaults/imcontrol_slm/info_oil.json
imswitch/_data/user_defaults/scripts/README.txt
imswitch/_data/user_defaults/scripts/example_import.py
imswitch/_data/user_defaults/scripts/example_imported.py
imswitch/_data/user_defaults/scripts/example_record.py
imswitch/imcommon/__init__.py
imswitch/imcommon/applaunch.py
imswitch/imcommon/controller/CheckUpdatesController.py
imswitch/imcommon/controller/ModuleCommunicationChannel.py
imswitch/imcommon/controller/MultiModuleWindowController.py
imswitch/imcommon/controller/PickDatasetsController.py
imswitch/imcommon/controller/PickModulesController.py
imswitch/imcommon/controller/__init__.py
imswitch/imcommon/controller/basecontrollers.py
imswitch/imcommon/framework/__init__.py
imswitch/imcommon/framework/base.py
imswitch/imcommon/framework/qt.py
imswitch/imcommon/model/SharedAttributes.py
imswitch/imcommon/model/VFileCollection.py
imswitch/imcommon/model/__init__.py
imswitch/imcommon/model/api.py
imswitch/imcommon/model/dirtools.py
imswitch/imcommon/model/logging.py
imswitch/imcommon/model/modulesconfigtools.py
imswitch/imcommon/model/ostools.py
imswitch/imcommon/model/pythontools.py
imswitch/imcommon/model/shortcut.py
imswitch/imcommon/view/AboutDialog.py
imswitch/imcommon/view/CheckUpdatesDialog.py
imswitch/imcommon/view/ModuleLoadErrorView.py
ImSwitch-2.0.0.dist-info/LICENSE
ImSwitch-2.0.0.dist-info/METADATA
ImSwitch-2.0.0.dist-info/WHEEL
ImSwitch-2.0.0.dist-info/entry_points.txt
ImSwitch-2.0.0.dist-info/top_level.txt
ImSwitch-2.0.0.dist-info/RECORD
