Metadata-Version: 2.1
Name: ImSwitch
Version: 2.0.0
Summary: Microscopy control
Home-page: https://github.com/kasasxav/ImSwitch
Author: Xavier Casas Moreno
Author-email: xaviercm@kth.se
Project-URL: Bug Tracker, https://github.com/kasasxav/ImSwitch/issues
Classifier: Programming Language :: Python :: 3
Classifier: License :: OSI Approved :: GNU General Public License v3 or later (GPLv3+)
Classifier: Operating System :: OS Independent
Requires-Python: >=3.8
License-File: LICENSE
Requires-Dist: coloredlogs (>=15)
Requires-Dist: colour-science (>=0.3)
Requires-Dist: dataclasses-json (>=0.5)
Requires-Dist: h5py (>=3)
Requires-Dist: lantzdev[qt] (>=0.5.2)
Requires-Dist: luddite (>=1)
Requires-Dist: napari[pyqt5]
Requires-Dist: nidaqmx (>=0.5.7)
Requires-Dist: numpy (>=1.19)
Requires-Dist: packaging (>=19)
Requires-Dist: psutil (>=5.4.8)
Requires-Dist: PyQt5 (>=5.15.2)
Requires-Dist: pyqtgraph (>=0.12.1)
Requires-Dist: microscope
Requires-Dist: pyserial (>=3.4)
Requires-Dist: QDarkStyle (>=3)
Requires-Dist: QScintilla (>=2.12)
Requires-Dist: qtpy (>=1.9)
Requires-Dist: requests (>=2.25)
Requires-Dist: scikit-image (>=0.18)
Requires-Dist: Send2Trash (>=1.8)
Requires-Dist: tifffile (>=2020.11.26)
Requires-Dist: ome-zarr (>=0.6.1)
Requires-Dist: Pyro5 (>=5.14)
Requires-Dist: fastAPI (>=0.86.0)
Requires-Dist: uvicorn[standard] (>=0.19.0)
